{
    "episode_number": 1,
    "name": "Naruto Shippuuden: Movie 3 - Hi no Ishi wo Tsugu Mono",
    "overview": "Hiruko adında, diğer ninjaların çakrasını emmeye yönelik bir jutsu geliştirmeye çalışan eski bir Kanoha ninjası yıllar sonra tekrar ortaya çıkar. Artık Chimera Tekniğini iyice geliştirerek Kekkei Genkai emebilecek duruma gelmiştir ve şimdi Hatake Kakashi'nin Kekkei Gankai'sini de emerek üstün ninja olmak istemektedir.  Köyünün olası bir savaşa girmemesi için tek çarenin kendini düşmana feda etmek olduğuna karar veren Kakashi, bu fikrini Tsunade'ye bildirir ve köyden ayrılır.  Ancak Naruto, böyle bir şeye izin vermeye niyetli değildir. Ne pahasına olursa olsun Kakashi'yi ve köyü kurtarmaya kararlıdır.",
    "air_date": "2009-08-01",
    "still_path": "/2HamMmwWN5Spc7cTaV9uDEY1tHS.jpg",
    "video_url": "1929144"

}